Metadata-Version: 2.1
Name: spherecluster2
Version: 0.2.1
Summary: Clustering on the unit hypersphere in scikit-learn.
Home-page: https://github.com/miquelmassot/spherecluster
Author: Jason Laska
Author-email: jason@claralabs.com
Maintainer: Miquel Massot
Maintainer-email: miquel.massot@gmail.com
License: MIT
Project-URL: Bug Reports, https://github.com/miquelmassot/spherecluster/issues
Project-URL: Source, https://github.com/miquelmassot/spherecluster
Classifier: Development Status :: 4 - Beta
Classifier: Intended Audience :: Developers
Classifier: Intended Audience :: Science/Research
Classifier: License :: OSI Approved :: MIT License
Classifier: Programming Language :: Python :: 3
Classifier: Topic :: Software Development
Classifier: Topic :: Software Development :: Libraries
Classifier: Topic :: Software Development :: Libraries :: Python Modules
License-File: LICENSE
